touchbar_lyric/__init__.py
touchbar_lyric/__main__.py
touchbar_lyric/service/__init__.py
touchbar_lyric/service/misc.py
touchbar_lyric/service/netease.py
touchbar_lyric/service/qq.py
touchbar_lyric/utility/__init__.py
touchbar_lyric-0.8.2.dist-info/METADATA
touchbar_lyric-0.8.2.dist-info/WHEEL
touchbar_lyric-0.8.2.dist-info/RECORD
