Metadata-Version: 2.1
Name: touchbar-lyric
Version: 0.8.2
Summary: Display lyrics on your touchbar with BTT
License: MIT
Author: Chenghao Mou
Author-email: mouchenghao@gmail.com
Requires-Python: >=3.7,<4.0
Classifier: License :: OSI Approved :: MIT License
Classifier: Programming Language :: Python :: 3
Classifier: Programming Language :: Python :: 3.7
Classifier: Programming Language :: Python :: 3.8
Classifier: Programming Language :: Python :: 3.9
Classifier: Programming Language :: Python :: 3.10
Classifier: Programming Language :: Python :: 3.11
Classifier: Programming Language :: Python :: 3.12
Requires-Dist: applescript (>=2021.2.9,<2022.0.0)
Requires-Dist: beautifulsoup4 (>=4.11.1,<5.0.0)
Requires-Dist: coverage (>=5.5,<6.0)
Requires-Dist: diskcache (>=5.2.1,<6.0.0)
Requires-Dist: hanziconv (>=0.3.2,<0.4.0)
Requires-Dist: loguru (>=0.5.3,<0.6.0)
Requires-Dist: pyaes (>=1.6.1,<2.0.0)
Requires-Dist: qqmusic-api (>=0.1,<0.2)
Requires-Dist: regex (>=2021.3.17,<2022.0.0)
Requires-Dist: strsimpy (>=0.2.0,<0.3.0)
Requires-Dist: typer (>=0.3.2,<0.4.0)
